{
  "tasks": [
    {
      "completed": false,
      "text": "Organize and clean",
      "description": "Organize and put things away",
      "dueDate": "2023-08-17",
      "group": "Organize Homework",
      "id": 5
    },
    {
      "completed": false,
      "text": "Clean room",
      "description": "Pick up after yourself",
      "dueDate": "2023-08-23",
      "group": "Organize Homework",
      "id": 6
    },
    {
      "completed": false,
      "text": "Meditate",
      "description": "Listen to guided audio",
      "dueDate": "2023-08-24",
      "group": "Habits",
      "id": 7
    },    
    {
      "completed": false,
      "text": "Read 2 research papers",
      "description": "Avance project",
      "dueDate": "2023-08-24",
      "group": "Work",
      "id": 7
    }
  ],
  "groups": [
    {
      "id": 1,
      "groupTitle": "Habits",
      "groupDescription": "Daily this to do",
      "groupDueDate": "31/08/2023"
    },
    {
      "id": 2,
      "groupTitle": "Work",
      "groupDescription": "Work this to do",
      "groupDueDate": "31/08/2023"
    }
  ]
}